ohmt/README.md
ohmt/__init__.py
ohmt/requirements.txt
ohmt/validation.py
ohmt/planes/README.md
ohmt/planes/__init__.py
ohmt/pruning/README.md
ohmt/pruning/__init__.py
ohmt/systems/README.md
ohmt/systems/__init__.py
ohmt/systems/utils.py
ohmt/trees/README.md
ohmt/trees/__init__.py
ohmt/trees/multivariate/__init__.py
ohmt/trees/multivariate/geometric.py
ohmt/trees/multivariate/modeltree.py
ohmt/trees/multivariate/oc1.py
ohmt/trees/multivariate/omnivariate.py
ohmt/trees/multivariate/optimaltree.py
ohmt/trees/splits/__init__.py
ohmt/trees/splits/evaluation.py
ohmt/trees/structure/__init__.py
ohmt/trees/structure/trees.py
ohmt/trees/univariate/__init__.py
ohmt/trees/univariate/c4.py
ohmt/trees/univariate/cart.py
ohmt/trees/univariate/dkm.py
ohmt-0.0.4.dist-info/METADATA
ohmt-0.0.4.dist-info/WHEEL
ohmt-0.0.4.dist-info/licenses/LICENSE
ohmt-0.0.4.dist-info/RECORD
