Metadata-Version: 2.3
Name: ohmt
Version: 0.0.4
Summary: Train decision trees, both univariate and multivariate.
Project-URL: Homepage, https://github.com/msetzu/oh-my-trees
Project-URL: Bug Tracker, https://github.com/msetzu/oh-my-trees/issues
Author-email: Mattia Setzu <mattia.setzu@unipi.it>
License-File: LICENSE
Classifier: Development Status :: 2 - Pre-Alpha
Classifier: Intended Audience :: Developers
Classifier: License :: OSI Approved :: GNU General Public License v3 or later (GPLv3+)
Classifier: Operating System :: OS Independent
Classifier: Programming Language :: Python :: 3.11
Classifier: Programming Language :: Python :: 3.12
Classifier: Programming Language :: Python :: 3.13
Requires-Python: >=3.11
Requires-Dist: asttokens==2.2.1
Requires-Dist: backcall==0.2.0
Requires-Dist: contourpy==1.0.6
Requires-Dist: cycler==0.11.0
Requires-Dist: decorator==5.1.1
Requires-Dist: executing==1.2.0
Requires-Dist: fire>=0.4.0
Requires-Dist: fonttools==4.38.0
Requires-Dist: graphviz==0.20.1
Requires-Dist: jedi==0.18.2
Requires-Dist: joblib==1.2.0
Requires-Dist: kiwisolver==1.4.4
Requires-Dist: more-itertools>=10.0.0
Requires-Dist: numpy>=1.23.0
Requires-Dist: packaging==22.0
Requires-Dist: parso==0.8.3
Requires-Dist: pexpect==4.8.0
Requires-Dist: pickleshare==0.7.5
Requires-Dist: pillow==9.3.0
Requires-Dist: prompt-toolkit>=3.0.36
Requires-Dist: ptyprocess==0.7.0
Requires-Dist: pure-eval==0.2.2
Requires-Dist: pygments==2.13.0
Requires-Dist: pyparsing==3.0.9
Requires-Dist: python-dateutil==2.8.2
Requires-Dist: scikit-learn>=1.0.0
Requires-Dist: scipy>=1.9.0
Requires-Dist: six==1.16.0
Requires-Dist: stack-data==0.6.2
Requires-Dist: termcolor==2.1.1
Requires-Dist: threadpoolctl==3.1.0
Requires-Dist: traitlets==5.7.1
Requires-Dist: wcwidth==0.2.5
